aliyunsdkrsimganalys/__init__.py
aliyunsdkrsimganalys/endpoint.py
aliyunsdkrsimganalys/request/__init__.py
aliyunsdkrsimganalys/request/v20190801/CreateImageRequest.py
aliyunsdkrsimganalys/request/v20190801/CreateTaskRequest.py
aliyunsdkrsimganalys/request/v20190801/DeleteImageRequest.py
aliyunsdkrsimganalys/request/v20190801/DeleteTaskRequest.py
aliyunsdkrsimganalys/request/v20190801/GetImageRequest.py
aliyunsdkrsimganalys/request/v20190801/GetShpInfoRequest.py
aliyunsdkrsimganalys/request/v20190801/GetTaskRequest.py
aliyunsdkrsimganalys/request/v20190801/ListTasksRequest.py
aliyunsdkrsimganalys/request/v20190801/__init__.py
aliyun_python_sdk_rsimganalys-4.3.1.dist-info/LICENSE
aliyun_python_sdk_rsimganalys-4.3.1.dist-info/METADATA
aliyun_python_sdk_rsimganalys-4.3.1.dist-info/WHEEL
aliyun_python_sdk_rsimganalys-4.3.1.dist-info/top_level.txt
aliyun_python_sdk_rsimganalys-4.3.1.dist-info/RECORD
